[
  {
    "type": "binary_operator",
    "named": true,
    "fields": {
      "left": {
        "multiple": false,
        "required": true,
        "types": [
          {
            "type": "binary_operator",
            "named": true
          },
          {
            "type": "boolean_operator",
            "named": true
          },
          {
            "type": "comparison_operator",
            "named": true
          },
          {
            "type": "identifier",
            "named": true
          },
          {
            "type": "matrix_definition",
            "named": true
          },
          {
            "type": "number",
            "named": true
          },
          {
            "type": "parenthesized_expression",
            "named": true
          },
          {
            "type": "postfix_operator",
            "named": true
          },
          {
            "type": "string",
            "named": true
          },
          {
            "type": "unary_operator",
            "named": true
          }
        ]
      },
      "operator": {
        "multiple": false,
        "required": true,
        "types": [
          {
            "type": "&",
            "named": false
          },
          {
            "type": "*",
            "named": false
          },
          {
            "type": "+",
            "named": false
          },
          {
            "type": "-",
            "named": false
          },
          {
            "type": ".*",
            "named": false
          },
          {
            "type": ".+",
            "named": false
          },
          {
            "type": ".-",
            "named": false
          },
          {
            "type": "./",
            "named": false
          },
          {
            "type": ".\\",
            "named": false
          },
          {
            "type": ".^",
            "named": false
          },
          {
            "type": "/",
            "named": false
          },
          {
            "type": "\\",
            "named": false
          },
          {
            "type": "^",
            "named": false
          },
          {
            "type": "|",
            "named": false
          }
        ]
      },
      "right": {
        "multiple": false,
        "required": true,
        "types": [
          {
            "type": "binary_operator",
            "named": true
          },
          {
            "type": "boolean_operator",
            "named": true
          },
          {
            "type": "comparison_operator",
            "named": true
          },
          {
            "type": "identifier",
            "named": true
          },
          {
            "type": "matrix_definition",
            "named": true
          },
          {
            "type": "number",
            "named": true
          },
          {
            "type": "parenthesized_expression",
            "named": true
          },
          {
            "type": "postfix_operator",
            "named": true
          },
          {
            "type": "string",
            "named": true
          },
          {
            "type": "unary_operator",
            "named": true
          }
        ]
      }
    }
  },
  {
    "type": "boolean_operator",
    "named": true,
    "fields": {
      "left": {
        "multiple": false,
        "required": true,
        "types": [
          {
            "type": "binary_operator",
            "named": true
          },
          {
            "type": "boolean_operator",
            "named": true
          },
          {
            "type": "comparison_operator",
            "named": true
          },
          {
            "type": "identifier",
            "named": true
          },
          {
            "type": "matrix_definition",
            "named": true
          },
          {
            "type": "number",
            "named": true
          },
          {
            "type": "parenthesized_expression",
            "named": true
          },
          {
            "type": "postfix_operator",
            "named": true
          },
          {
            "type": "string",
            "named": true
          },
          {
            "type": "unary_operator",
            "named": true
          }
        ]
      },
      "operator": {
        "multiple": false,
        "required": true,
        "types": [
          {
            "type": "&&",
            "named": false
          },
          {
            "type": "||",
            "named": false
          }
        ]
      },
      "right": {
        "multiple": false,
        "required": true,
        "types": [
          {
            "type": "binary_operator",
            "named": true
          },
          {
            "type": "boolean_operator",
            "named": true
          },
          {
            "type": "comparison_operator",
            "named": true
          },
          {
            "type": "identifier",
            "named": true
          },
          {
            "type": "matrix_definition",
            "named": true
          },
          {
            "type": "number",
            "named": true
          },
          {
            "type": "parenthesized_expression",
            "named": true
          },
          {
            "type": "postfix_operator",
            "named": true
          },
          {
            "type": "string",
            "named": true
          },
          {
            "type": "unary_operator",
            "named": true
          }
        ]
      }
    }
  },
  {
    "type": "comparison_operator",
    "named": true,
    "fields": {
      "operators": {
        "multiple": true,
        "required": true,
        "types": [
          {
            "type": "<",
            "named": false
          },
          {
            "type": "<=",
            "named": false
          },
          {
            "type": "==",
            "named": false
          },
          {
            "type": ">",
            "named": false
          },
          {
            "type": ">=",
            "named": false
          },
          {
            "type": "~=",
            "named": false
          }
        ]
      }
    },
    "children": {
      "multiple": true,
      "required": true,
      "types": [
        {
          "type": "binary_operator",
          "named": true
        },
        {
          "type": "boolean_operator",
          "named": true
        },
        {
          "type": "comparison_operator",
          "named": true
        },
        {
          "type": "identifier",
          "named": true
        },
        {
          "type": "matrix_definition",
          "named": true
        },
        {
          "type": "number",
          "named": true
        },
        {
          "type": "parenthesized_expression",
          "named": true
        },
        {
          "type": "postfix_operator",
          "named": true
        },
        {
          "type": "string",
          "named": true
        },
        {
          "type": "unary_operator",
          "named": true
        }
      ]
    }
  },
  {
    "type": "matrix_definition",
    "named": true,
    "fields": {},
    "children": {
      "multiple": true,
      "required": false,
      "types": [
        {
          "type": "binary_operator",
          "named": true
        },
        {
          "type": "boolean_operator",
          "named": true
        },
        {
          "type": "comparison_operator",
          "named": true
        },
        {
          "type": "identifier",
          "named": true
        },
        {
          "type": "matrix_definition",
          "named": true
        },
        {
          "type": "number",
          "named": true
        },
        {
          "type": "parenthesized_expression",
          "named": true
        },
        {
          "type": "postfix_operator",
          "named": true
        },
        {
          "type": "string",
          "named": true
        },
        {
          "type": "unary_operator",
          "named": true
        }
      ]
    }
  },
  {
    "type": "number",
    "named": true,
    "fields": {}
  },
  {
    "type": "parenthesized_expression",
    "named": true,
    "fields": {},
    "children": {
      "multiple": false,
      "required": true,
      "types": [
        {
          "type": "binary_operator",
          "named": true
        },
        {
          "type": "boolean_operator",
          "named": true
        },
        {
          "type": "comparison_operator",
          "named": true
        },
        {
          "type": "identifier",
          "named": true
        },
        {
          "type": "matrix_definition",
          "named": true
        },
        {
          "type": "number",
          "named": true
        },
        {
          "type": "parenthesized_expression",
          "named": true
        },
        {
          "type": "postfix_operator",
          "named": true
        },
        {
          "type": "string",
          "named": true
        },
        {
          "type": "unary_operator",
          "named": true
        }
      ]
    }
  },
  {
    "type": "postfix_operator",
    "named": true,
    "fields": {
      "argument": {
        "multiple": false,
        "required": true,
        "types": [
          {
            "type": "binary_operator",
            "named": true
          },
          {
            "type": "boolean_operator",
            "named": true
          },
          {
            "type": "comparison_operator",
            "named": true
          },
          {
            "type": "identifier",
            "named": true
          },
          {
            "type": "matrix_definition",
            "named": true
          },
          {
            "type": "number",
            "named": true
          },
          {
            "type": "parenthesized_expression",
            "named": true
          },
          {
            "type": "postfix_operator",
            "named": true
          },
          {
            "type": "string",
            "named": true
          },
          {
            "type": "unary_operator",
            "named": true
          }
        ]
      },
      "operator": {
        "multiple": false,
        "required": true,
        "types": [
          {
            "type": "'",
            "named": false
          },
          {
            "type": ".'",
            "named": false
          }
        ]
      }
    }
  },
  {
    "type": "source_file",
    "named": true,
    "fields": {
      "comment": {
        "multiple": true,
        "required": false,
        "types": [
          {
            "type": "comment",
            "named": true
          }
        ]
      }
    },
    "children": {
      "multiple": true,
      "required": false,
      "types": [
        {
          "type": "binary_operator",
          "named": true
        },
        {
          "type": "boolean_operator",
          "named": true
        },
        {
          "type": "comparison_operator",
          "named": true
        },
        {
          "type": "identifier",
          "named": true
        },
        {
          "type": "matrix_definition",
          "named": true
        },
        {
          "type": "number",
          "named": true
        },
        {
          "type": "parenthesized_expression",
          "named": true
        },
        {
          "type": "postfix_operator",
          "named": true
        },
        {
          "type": "string",
          "named": true
        },
        {
          "type": "unary_operator",
          "named": true
        }
      ]
    }
  },
  {
    "type": "string",
    "named": true,
    "fields": {}
  },
  {
    "type": "unary_operator",
    "named": true,
    "fields": {
      "argument": {
        "multiple": false,
        "required": true,
        "types": [
          {
            "type": "binary_operator",
            "named": true
          },
          {
            "type": "boolean_operator",
            "named": true
          },
          {
            "type": "comparison_operator",
            "named": true
          },
          {
            "type": "identifier",
            "named": true
          },
          {
            "type": "matrix_definition",
            "named": true
          },
          {
            "type": "number",
            "named": true
          },
          {
            "type": "parenthesized_expression",
            "named": true
          },
          {
            "type": "postfix_operator",
            "named": true
          },
          {
            "type": "string",
            "named": true
          },
          {
            "type": "unary_operator",
            "named": true
          }
        ]
      },
      "operator": {
        "multiple": false,
        "required": true,
        "types": [
          {
            "type": "+",
            "named": false
          },
          {
            "type": "-",
            "named": false
          },
          {
            "type": "~",
            "named": false
          }
        ]
      }
    }
  },
  {
    "type": "\n",
    "named": false
  },
  {
    "type": "\r",
    "named": false
  },
  {
    "type": "\"",
    "named": false
  },
  {
    "type": "&",
    "named": false
  },
  {
    "type": "&&",
    "named": false
  },
  {
    "type": "'",
    "named": false
  },
  {
    "type": "(",
    "named": false
  },
  {
    "type": ")",
    "named": false
  },
  {
    "type": "*",
    "named": false
  },
  {
    "type": "+",
    "named": false
  },
  {
    "type": ",",
    "named": false
  },
  {
    "type": "-",
    "named": false
  },
  {
    "type": ".'",
    "named": false
  },
  {
    "type": ".*",
    "named": false
  },
  {
    "type": ".+",
    "named": false
  },
  {
    "type": ".-",
    "named": false
  },
  {
    "type": "./",
    "named": false
  },
  {
    "type": ".\\",
    "named": false
  },
  {
    "type": ".^",
    "named": false
  },
  {
    "type": "/",
    "named": false
  },
  {
    "type": ";",
    "named": false
  },
  {
    "type": "<",
    "named": false
  },
  {
    "type": "<=",
    "named": false
  },
  {
    "type": "==",
    "named": false
  },
  {
    "type": ">",
    "named": false
  },
  {
    "type": ">=",
    "named": false
  },
  {
    "type": "[",
    "named": false
  },
  {
    "type": "\\",
    "named": false
  },
  {
    "type": "]",
    "named": false
  },
  {
    "type": "^",
    "named": false
  },
  {
    "type": "comment",
    "named": true
  },
  {
    "type": "identifier",
    "named": true
  },
  {
    "type": "|",
    "named": false
  },
  {
    "type": "||",
    "named": false
  },
  {
    "type": "~",
    "named": false
  },
  {
    "type": "~=",
    "named": false
  }
]